{"blog_2026_2026-1_unicode-flags-for-windows.md":"D7rgnwuB","blog_archives.md":"a-SuHvUk","blog_series.md":"BlCfibK_","blog_tags.md":"BXIEibUQ","homepage.md":"MERUhsIy","index.md":"BnZeXIcB","储物间_1-搜索引擎.md":"Bjy4_a4C","储物间_10-网页浏览器.md":"CRqfVwQi","储物间_11-维基媒体.md":"CLVzxlQS","储物间_12-工具箱.md":"B3LyHioj","储物间_13-tg频道推荐.md":"CX57m1oO","储物间_2-问答导航.md":"BOaJgdIe","储物间_3-百科全书.md":"DWuOf1xc","储物间_4-bt导航.md":"KNfKVcwT","储物间_5-网盘服务.md":"B7XPdgzf","储物间_6-音乐导航.md":"9DX0GNbf","储物间_7-社交平台.md":"DDUZLnMH","储物间_8-图书馆.md":"DGjt752f","储物间_9-图片资源.md":"DIgtGdwa","储物间_储物间目录.md":"Bd90xWuH","墙外指南_名词解释.md":"i9clMfSj","墙外指南_墙外指南目录.md":"CFna0Az8","墙外指南_推荐机场_2026_2026-1.md":"OToZXqko","墙外指南_推荐机场_gfw-telegram.md":"CuB77Quj","墙外指南_教程_appleid.md":"DuFF3G5s","墙外指南_教程_加速github下载.md":"BAEnvZZV","墙外指南_软件下载_proxy-client_clash.md":"DORiB9P2","墙外指南_软件下载_proxy-client_clashmetaforandroid.md":"Cdg-yz8L","墙外指南_软件下载_proxy-client_clashmi.md":"gJyMvJh0","墙外指南_软件下载_proxy-client_clashvergerev.md":"CGU1s7Sw","墙外指南_软件下载_proxy-client_client.md":"BHlSYlBh","墙外指南_软件下载_proxy-client_flclash.md":"mv1Mux0r","墙外指南_软件下载_proxy-client_hiddfy.md":"upZbVAGP","墙外指南_软件下载_proxy-client_karing.md":"Dz7ULMkz","墙外指南_镜像_github.md":"BddrxmHU","墙外指南_镜像_wikipedia.md":"BSxUilSz"}
